ultipa/__init__.py
ultipa/connection/__init__.py
ultipa/connection/autoNet_extra.py
ultipa/connection/connection.py
ultipa/connection/connectionPool.py
ultipa/connection/connectionPoolMaker.py
ultipa/connection/connection_base.py
ultipa/connection/download_extra.py
ultipa/connection/edge_extra.py
ultipa/connection/export_extra.py
ultipa/connection/graph_extra.py
ultipa/connection/index_extra.py
ultipa/connection/lte_ufe_extra.py
ultipa/connection/nodeSpread_extra.py
ultipa/connection/node_extra.py
ultipa/connection/policy_extra.py
ultipa/connection/property_extra.py
ultipa/connection/schema_extra.py
ultipa/connection/searchAB_extra.py
ultipa/connection/searchKhop_extra.py
ultipa/connection/task_extra.py
ultipa/connection/template_extra.py
ultipa/connection/truncate_extra.py
ultipa/connection/user_extra.py
ultipa/connection/algo/__init__.py
ultipa/connection/algo/algo_extra.py
ultipa/connection/algo/algo_params4.py
ultipa/connection/algo/algos_params.py
ultipa/connection/algo/community_extra.py
ultipa/connection/algo/degrees_extra.py
ultipa/connection/algo/embedding_extra.py
ultipa/connection/algo/makeAlgoClass.py
ultipa/printer/__init__.py
ultipa/printer/prettyPrint.py
ultipa/proto/__init__.py
ultipa/proto/ultipa_pb2.py
ultipa/proto/ultipa_pb2_grpc.py
ultipa/types/__init__.py
ultipa/types/types.py
ultipa/types/types_request.py
ultipa/types/types_response.py
ultipa/utils/ResposeFormat.py
ultipa/utils/__init__.py
ultipa/utils/checkStrTime.py
ultipa/utils/common.py
ultipa/utils/convert.py
ultipa/utils/errors.py
ultipa/utils/fileSize.py
ultipa/utils/format.py
ultipa/utils/logger.py
ultipa/utils/password2md5.py
ultipa/utils/privileges.py
ultipa/utils/raftRetry.py
ultipa/utils/serialize.py
ultipa/utils/typeCheck.py
ultipa/utils/ultipaSchedule.py
ultipa/utils/ultipa_datetime.py
ultipa/utils/uql_marker.py
ultipa/utils/ufilter/__init__.py
ultipa/utils/ufilter/new_ufilter.py
ultipa/utils/ufilter/ufilter.py
test_ultipa-4.2.1.dist-info/METADATA
test_ultipa-4.2.1.dist-info/WHEEL
test_ultipa-4.2.1.dist-info/top_level.txt
test_ultipa-4.2.1.dist-info/RECORD
